flowvid/__init__.py
flowvid/__main__.py
flowvid/core/__init__.py
flowvid/core/filterable.py
flowvid/core/conversion/__init__.py
flowvid/core/conversion/epe_to_rgb.py
flowvid/core/conversion/flow_to_rgb.py
flowvid/core/conversion/split_uv.py
flowvid/core/filters/__init__.py
flowvid/core/filters/accum_flow.py
flowvid/core/filters/base_filter.py
flowvid/core/filters/normalize_epe.py
flowvid/core/filters/normalize_flow.py
flowvid/core/operators/__init__.py
flowvid/core/operators/add_flow_points.py
flowvid/core/operators/add_flow_rect.py
flowvid/core/operators/base_operator.py
flowvid/core/operators/draw_flow_arrows.py
flowvid/core/operators/draw_points.py
flowvid/core/operators/draw_rectangle.py
flowvid/core/operators/endpoint_error.py
flowvid/core/operators/synthesize_image.py
flowvid/core/operators/track_from_first.py
flowvid/core/util/__init__.py
flowvid/core/util/add_flow.py
flowvid/core/util/color_flow.py
flowvid/core/util/convert_to_axes.py
flowvid/core/util/image_draw.py
flowvid/input/__init__.py
flowvid/input/file_input.py
flowvid/input/flo_data.py
flowvid/input/point_input.py
flowvid/input/rgb_data.py
flowvid/input/track_points.py
flowvid/output/__init__.py
flowvid/output/flo_output.py
flowvid/output/image_output.py
flowvid/output/plot_show.py
flowvid/output/video_output.py
flowvid/presets/__init__.py
flowvid/presets/preset_color_epe.py
flowvid/presets/preset_color_flow.py
flowvid/presets/preset_flow_arrows.py
flowvid/presets/preset_plot_epe.py
flowvid/presets/preset_track_points.py
flowvid/presets/preset_track_side_by_side.py
flowvid/presets/utils.py
flowvid-0.4.1.dist-info/LICENSE
flowvid-0.4.1.dist-info/METADATA
flowvid-0.4.1.dist-info/WHEEL
flowvid-0.4.1.dist-info/top_level.txt
flowvid-0.4.1.dist-info/RECORD
