Metadata-Version: 2.1
Name: flowvid
Version: 0.4.1
Summary: Optical Flow video tools
Home-page: https://github.com/diegoroyo/flowvid
Author: Diego Royo
Author-email: 740388@unizar.es
License: UNKNOWN
Platform: UNKNOWN
Classifier: Programming Language :: Python :: 3
Classifier: License :: OSI Approved :: GNU General Public License v3 (GPLv3)
Classifier: Operating System :: OS Independent
Requires-Python: >=3.6
